{
  "id":"10024"
 ,"Identification":{
    "Name":"Feedback"
   ,"Alias":"FEEDBACK1"
   ,"Title":"Feedback"
   ,"Page Group":"Administration (54557183068995950)"
  }
 ,"Appearance":{
    "User Interface":"Desktop (54551875302995858)"
   ,"Page Mode":"Modal Dialog"
   ,"Dialog Template":"Theme Default"
  }
 ,"Dialog":{
    "Chained":false
  }
 ,"Navigation Menu":{
    "Override User Interface Level":false
  }
 ,"Navigation":{
    "Cursor Focus":"Do not focus cursor"
   ,"Warn on Unsaved Changes":true
  }
 ,"JavaScript":{
    "Function and Global Variable Declaration":"var htmldb_delete_message=\u0027\"DELETE_CONFIRM_MSG\"\u0027;"
  }
 ,"CSS":{
    "Inline":"\/* Color feedback rating icons *\/\n.feedback-positive { color: #4caf50; }\n.feedback-neutral { color: #eb9f41; }\n.feedback-negative { color: #f44336; }"
  }
 ,"Security":{
    "Authorization Scheme":"Administration Rights (54555301792995935)"
   ,"Authentication":"Page Requires Authentication"
   ,"Deep Linking":"Application Default"
   ,"Page Access Protection":"Arguments Must Have Checksum"
   ,"Form Auto Complete":"Off"
   ,"Browser Cache":"Application Default"
  }
 ,"Session Management":{
    "Rejoin Sessions":"Application Default"
  }
 ,"Advanced":{
    "Enable duplicate page submissions":"Yes - Enable page to be re-posted"
   ,"Reload on Submit":"Only for Success"
  }
 ,"Server Cache":{
    "Caching":"Disabled"
  }
 ,"Configuration":{
    "Build Option":"Feature: Feedback (54553386857995923)"
  }
 ,"Regions":[
    {
      "id":"54600279238996129"
     ,"Identification":{
        "Title":"Form Items Region"
       ,"Type":"Static Content"
      }
     ,"Layout":{
        "Sequence":10
       ,"Parent Region":"No Parent"
       ,"Position":"BODY"
       ,"Start New Layout":false
       ,"Start New Row":true
       ,"Column":"Automatic"
       ,"New Column":true
       ,"Column Span":"Automatic"
      }
     ,"Appearance":{
        "Template":"Blank with Attributes (54431268247995715)"
       ,"Template Options":[
          "#DEFAULT#"
         ,"t-Form--stretchInputs"
        ]
       ,"Render Components":"Above Content"
      }
     ,"Advanced":{
        "Region Display Selector":false
       ,"Exclude Title from Translation":false
      }
     ,"Server Cache":{
        "Caching":"Disabled"
      }
     ,"Customization":{
        "Customizable":"Not Customizable By End Users"
      }
     ,"Attributes":{
        "Settings":{
          "Output As":"HTML"
         ,"Expand Shortcuts":false
        }
      }
    }
   ,{
      "id":"54600284833996129"
     ,"Identification":{
        "Title":"Buttons Region"
       ,"Type":"Static Content"
      }
     ,"Layout":{
        "Sequence":10
       ,"Parent Region":"No Parent"
       ,"Position":"REGION_POSITION_03"
       ,"Start New Layout":false
       ,"Start New Row":true
       ,"Column":"Automatic"
       ,"New Column":true
       ,"Column Span":"Automatic"
      }
     ,"Appearance":{
        "Template":"Buttons Container (54432201299995716)"
       ,"Template Options":[
          "#DEFAULT#"
        ]
       ,"Render Components":"Above Content"
      }
     ,"Advanced":{
        "Region Display Selector":false
       ,"Exclude Title from Translation":false
      }
     ,"Server Cache":{
        "Caching":"Disabled"
      }
     ,"Customization":{
        "Customizable":"Not Customizable By End Users"
      }
     ,"Attributes":{
        "Settings":{
          "Output As":"HTML"
         ,"Expand Shortcuts":false
        }
      }
    }
  ]
 ,"Page Items":[
    {
      "id":"54611501140996144"
     ,"Identification":{
        "Name":"P10024_ID"
       ,"Type":"Hidden"
      }
     ,"Settings":{
        "Value Protected":true
      }
     ,"Layout":{
        "Sequence":10
       ,"Region":"Form Items Region (54600279238996129)"
       ,"Position":"BODY"
      }
     ,"Advanced":{
        "Warn on Unsaved Changes":"Page Default"
      }
     ,"Source":{
        "Type":"Null"
       ,"Used":"Only when current value in session state is null"
       ,"Maintain Session State":"Per Session (Disk)"
      }
     ,"Security":{
        "Session State Protection":"Checksum Required - Session Level"
       ,"Store value encrypted in session state":false
       ,"Restricted Characters":"All characters can be saved."
      }
    }
   ,{
      "id":"54611906610996144"
     ,"Identification":{
        "Name":"P10024_PAGE_ID"
       ,"Type":"Display Only"
      }
     ,"Label":{
        "Label":"Page"
       ,"Alignment":"Left"
      }
     ,"Settings":{
        "Format":"Plain Text"
       ,"Based On":"Item Value"
       ,"Show Line Breaks":true
       ,"Send On Page Submit":true
      }
     ,"Layout":{
        "Sequence":20
       ,"Region":"Form Items Region (54600279238996129)"
       ,"Position":"BODY"
       ,"Alignment":"Left"
       ,"Start New Layout":false
       ,"Start New Row":true
       ,"Column":"Automatic"
       ,"New Column":true
       ,"Column Span":"Automatic"
       ,"Label Column Span":"Page Template Default"
      }
     ,"Appearance":{
        "Template":"Optional - Floating (54524856483995797)"
      }
     ,"Advanced":{
        "Warn on Unsaved Changes":"Page Default"
      }
     ,"Source":{
        "Type":"Null"
       ,"Used":"Only when current value in session state is null"
       ,"Maintain Session State":"Per Session (Disk)"
      }
     ,"Security":{
        "Session State Protection":"Unrestricted"
       ,"Store value encrypted in session state":false
       ,"Restricted Characters":"All characters can be saved."
      }
    }
   ,{
      "id":"54612328399996145"
     ,"Identification":{
        "Name":"P10024_FILED"
       ,"Type":"Display Only"
      }
     ,"Label":{
        "Label":"Filed"
       ,"Alignment":"Left"
      }
     ,"Settings":{
        "Format":"Plain Text"
       ,"Based On":"Item Value"
       ,"Show Line Breaks":true
       ,"Send On Page Submit":true
      }
     ,"Layout":{
        "Sequence":30
       ,"Region":"Form Items Region (54600279238996129)"
       ,"Position":"BODY"
       ,"Alignment":"Left"
       ,"Start New Layout":false
       ,"Start New Row":false
       ,"Column":"Automatic"
       ,"New Column":true
       ,"Column Span":"Automatic"
       ,"Label Column Span":"Page Template Default"
      }
     ,"Appearance":{
        "Template":"Optional - Floating (54524856483995797)"
      }
     ,"Advanced":{
        "Warn on Unsaved Changes":"Page Default"
      }
     ,"Source":{
        "Type":"Null"
       ,"Used":"Only when current value in session state is null"
       ,"Maintain Session State":"Per Session (Disk)"
      }
     ,"Security":{
        "Session State Protection":"Unrestricted"
       ,"Store value encrypted in session state":false
       ,"Restricted Characters":"All characters can be saved."
      }
    }
   ,{
      "id":"54612699757996145"
     ,"Identification":{
        "Name":"P10024_RATING_ICON"
       ,"Type":"Display Only"
      }
     ,"Label":{
        "Label":"Rating"
       ,"Alignment":"Left"
      }
     ,"Settings":{
        "Format":"Plain Text"
       ,"Based On":"Item Value"
       ,"Show Line Breaks":true
       ,"Send On Page Submit":true
      }
     ,"Layout":{
        "Sequence":40
       ,"Region":"Form Items Region (54600279238996129)"
       ,"Position":"BODY"
       ,"Alignment":"Left"
       ,"Start New Layout":false
       ,"Start New Row":false
       ,"Column":"Automatic"
       ,"New Column":true
       ,"Column Span":"Automatic"
       ,"Label Column Span":"Page Template Default"
      }
     ,"Appearance":{
        "Template":"Optional - Floating (54524856483995797)"
      }
     ,"Advanced":{
        "Warn on Unsaved Changes":"Page Default"
      }
     ,"Source":{
        "Type":"Null"
       ,"Used":"Only when current value in session state is null"
       ,"Maintain Session State":"Per Session (Disk)"
      }
     ,"Security":{
        "Session State Protection":"Unrestricted"
       ,"Store value encrypted in session state":false
       ,"Restricted Characters":"All characters can be saved."
      }
    }
   ,{
      "id":"54613159476996147"
     ,"Identification":{
        "Name":"P10024_FEEDBACK"
       ,"Type":"Display Only"
      }
     ,"Label":{
        "Label":"Feedback"
       ,"Alignment":"Left"
      }
     ,"Settings":{
        "Format":"Plain Text"
       ,"Based On":"Item Value"
       ,"Show Line Breaks":true
       ,"Send On Page Submit":true
      }
     ,"Layout":{
        "Sequence":50
       ,"Region":"Form Items Region (54600279238996129)"
       ,"Position":"BODY"
       ,"Alignment":"Left"
       ,"Start New Layout":false
       ,"Start New Row":true
       ,"Column":"Automatic"
       ,"New Column":true
       ,"Column Span":"Automatic"
       ,"Label Column Span":"Page Template Default"
      }
     ,"Appearance":{
        "Template":"Optional - Floating (54524856483995797)"
      }
     ,"Advanced":{
        "Warn on Unsaved Changes":"Page Default"
      }
     ,"Source":{
        "Type":"Null"
       ,"Used":"Only when current value in session state is null"
       ,"Maintain Session State":"Per Session (Disk)"
      }
     ,"Security":{
        "Session State Protection":"Unrestricted"
       ,"Store value encrypted in session state":false
       ,"Restricted Characters":"All characters can be saved."
      }
    }
   ,{
      "id":"54613507715996147"
     ,"Identification":{
        "Name":"P10024_RESPONSE"
       ,"Type":"Textarea"
      }
     ,"Label":{
        "Label":"Response"
       ,"Alignment":"Left"
      }
     ,"Settings":{
        "Resizable":true
       ,"Auto-Height":false
       ,"Character Counter":false
       ,"Trim Spaces":"Leading and Trailing"
      }
     ,"Layout":{
        "Sequence":60
       ,"Region":"Form Items Region (54600279238996129)"
       ,"Position":"BODY"
       ,"Alignment":"Left"
       ,"Start New Layout":false
       ,"Start New Row":true
       ,"Column":"Automatic"
       ,"New Column":true
       ,"Column Span":"Automatic"
       ,"Label Column Span":"Page Template Default"
      }
     ,"Appearance":{
        "Template":"Optional - Floating (54524856483995797)"
       ,"Width":64
       ,"Height":4
      }
     ,"Validation":{
        "Value Required":false
       ,"Maximum Length":4000
      }
     ,"Advanced":{
        "Warn on Unsaved Changes":"Page Default"
      }
     ,"Source":{
        "Type":"Null"
       ,"Used":"Only when current value in session state is null"
       ,"Maintain Session State":"Per Session (Disk)"
      }
     ,"Quick Picks":{
        "Show Quick Picks":false
      }
     ,"Security":{
        "Session State Protection":"Unrestricted"
       ,"Store value encrypted in session state":false
       ,"Restricted Characters":"All characters can be saved."
      }
    }
   ,{
      "id":"54613933729996148"
     ,"Identification":{
        "Name":"P10024_FEEDBACK_STATUS"
       ,"Type":"Select List"
      }
     ,"Label":{
        "Label":"Status"
       ,"Alignment":"Left"
      }
     ,"Settings":{
        "Page Action on Selection":"None"
       ,"Allow Multi Selection":false
      }
     ,"Layout":{
        "Sequence":70
       ,"Region":"Form Items Region (54600279238996129)"
       ,"Position":"BODY"
       ,"Alignment":"Left"
       ,"Start New Layout":false
       ,"Start New Row":true
       ,"Column":"Automatic"
       ,"New Column":true
       ,"Column Span":"Automatic"
       ,"Label Column Span":"Page Template Default"
      }
     ,"Appearance":{
        "Template":"Optional - Floating (54524856483995797)"
      }
     ,"Validation":{
        "Value Required":false
      }
     ,"List of Values":{
        "Type":"Shared Component"
       ,"List of Values":"FEEDBACK_STATUS (54614072353996148)"
       ,"Display Extra Values":false
       ,"Display Null Value":false
      }
     ,"Advanced":{
        "Warn on Unsaved Changes":"Page Default"
      }
     ,"Source":{
        "Type":"Null"
       ,"Used":"Only when current value in session state is null"
       ,"Maintain Session State":"Per Session (Disk)"
      }
     ,"Quick Picks":{
        "Show Quick Picks":false
      }
     ,"Security":{
        "Session State Protection":"Unrestricted"
       ,"Store value encrypted in session state":false
       ,"Restricted Characters":"All characters can be saved."
      }
    }
   ,{
      "id":"54616206664996149"
     ,"Identification":{
        "Name":"P10024_USER_AGENT"
       ,"Type":"Display Only"
      }
     ,"Label":{
        "Label":"User Agent"
       ,"Alignment":"Left"
      }
     ,"Settings":{
        "Format":"Plain Text"
       ,"Based On":"Item Value"
       ,"Show Line Breaks":true
       ,"Send On Page Submit":true
      }
     ,"Layout":{
        "Sequence":100
       ,"Region":"Form Items Region (54600279238996129)"
       ,"Position":"BODY"
       ,"Alignment":"Left"
       ,"Start New Layout":false
       ,"Start New Row":true
       ,"Column":"Automatic"
       ,"New Column":true
       ,"Column Span":"Automatic"
       ,"Label Column Span":"Page Template Default"
      }
     ,"Appearance":{
        "Template":"Optional - Floating (54524856483995797)"
      }
     ,"Advanced":{
        "Warn on Unsaved Changes":"Page Default"
      }
     ,"Source":{
        "Type":"Null"
       ,"Used":"Only when current value in session state is null"
       ,"Maintain Session State":"Per Session (Disk)"
      }
     ,"Security":{
        "Session State Protection":"Unrestricted"
       ,"Store value encrypted in session state":false
       ,"Restricted Characters":"All characters can be saved."
      }
    }
  ]
 ,"Buttons":[
    {
      "id":"54600408228996129"
     ,"Identification":{
        "Button Name":"SAVE"
       ,"Label":"Apply Changes"
      }
     ,"Layout":{
        "Sequence":10
       ,"Region":"Buttons Region (54600284833996129)"
       ,"Position":"CREATE"
       ,"Start New Layout":false
       ,"Start New Row":true
       ,"Column":"Automatic"
       ,"New Column":true
       ,"Column Span":"Automatic"
      }
     ,"Appearance":{
        "Button Template":"Text (54527310383995804)"
       ,"Hot":true
       ,"Template Options":[
          "#DEFAULT#"
         ,"t-Button--gapLeft"
        ]
      }
     ,"Behavior":{
        "Action":"Submit Page"
       ,"Execute Validations":true
       ,"Warn on Unsaved Changes":"Do Not Check"
      }
    }
   ,{
      "id":"54600502277996129"
     ,"Identification":{
        "Button Name":"CANCEL"
       ,"Label":"Cancel"
      }
     ,"Layout":{
        "Sequence":20
       ,"Region":"Buttons Region (54600284833996129)"
       ,"Position":"EDIT"
       ,"Start New Layout":false
       ,"Start New Row":true
       ,"Column":"Automatic"
       ,"New Column":true
       ,"Column Span":"Automatic"
      }
     ,"Appearance":{
        "Button Template":"Text (54527310383995804)"
       ,"Hot":false
       ,"Template Options":[
          "#DEFAULT#"
        ]
      }
     ,"Behavior":{
        "Action":"Defined by Dynamic Action"
       ,"Execute Validations":true
      }
    }
   ,{
      "id":"54600636410996129"
     ,"Identification":{
        "Button Name":"DELETE"
       ,"Label":"Delete"
      }
     ,"Layout":{
        "Sequence":30
       ,"Region":"Buttons Region (54600284833996129)"
       ,"Position":"EDIT"
       ,"Start New Layout":false
       ,"Start New Row":true
       ,"Column":"Automatic"
       ,"New Column":true
       ,"Column Span":"Automatic"
      }
     ,"Appearance":{
        "Button Template":"Text (54527310383995804)"
       ,"Hot":false
       ,"Template Options":[
          "#DEFAULT#"
         ,"t-Button--danger"
         ,"t-Button--simple"
        ]
      }
     ,"Behavior":{
        "Action":"Redirect to URL"
       ,"Target":"javascript:apex.confirm(htmldb_delete_message,\u0027DELETE\u0027);"
       ,"Execute Validations":true
       ,"Warn on Unsaved Changes":"Do Not Check"
       ,"Database Action":"SQL DELETE action"
      }
     ,"Server-side Condition":{
        "Type":"Item is NOT NULL"
       ,"Item":"P10024_ID"
      }
    }
  ]
 ,"Dynamic Actions":[
    {
      "id":"54600730581996129"
     ,"Identification":{
        "Name":"Cancel Dialog"
      }
     ,"Execution Options":{
        "Sequence":10
      }
     ,"When":{
        "Event":"EVENT.EVENT.BROWSER.CLICK"
       ,"Selection Type":"Button"
       ,"Button":"CANCEL (54600502277996129)"
      }
     ,"Advanced":{
        "Event Scope":"Static"
      }
     ,"Actions":[
        {
          "id":"54617054814996149"
         ,"Identification":{
            "Action":"Cancel Dialog"
          }
         ,"Execution Options":{
            "Sequence":10
           ,"Event":"Cancel Dialog (54600730581996129)"
           ,"Fire When Event Result Is":"True"
           ,"Fire on Initialization":false
          }
        }
      ]
    }
  ]
 ,"Processes":[
    {
      "id":"54617528174996150"
     ,"Identification":{
        "Name":"Load Data"
       ,"Type":"Execute Code"
      }
     ,"Source":{
        "Location":"Local Database"
       ,"Language":"PL\/SQL"
       ,"PL\/SQL Code":"for c1 in (\n   select page_id,\n          page_name,\n          case feedback_rating\n                when 1 then \u0027\u003Cspan class=\"fa fa-frown-o feedback-negative\" aria-hidden=\"true\" title=\"Negative\"\u003E\u003C\/span\u003E\u0027 \n                when 2 then \u0027\u003Cspan class=\"fa fa-emoji-neutral feedback-neutral\" aria-hidden=\"true\" title=\"Neutral\"\u003E\u003C\/span\u003E\u0027  \n                when 3 then \u0027\u003Cspan class=\"fa fa-smile-o feedback-positive\" aria-hidden=\"true\" title=\"Positive\"\u003E\u003C\/span\u003E\u0027 \n                end rating_icon,\n          lower(created_by) || \u0027 - \u0027 || apex_util.get_since(created_on) filed,\n          feedback,\n          public_response,\n          feedback_status,\n          http_user_agent\n     from apex_team_feedback\n    where feedback_id = :P10024_ID\n) loop\n   :P10024_PAGE_ID := c1.page_id||\u0027. \u0027||c1.page_name;\n   :P10024_FILED := c1.filed;\n   :P10024_RATING_ICON := c1.rating_icon;\n   :P10024_FEEDBACK := c1.feedback;\n   :P10024_RESPONSE := c1.public_response;\n   :P10024_FEEDBACK_STATUS := c1.feedback_status;\n   :P10024_USER_AGENT := c1.http_user_agent;\nend loop;"
      }
     ,"Execution Options":{
        "Sequence":10
       ,"Point":"After Header"
       ,"Run Process":"Once Per Page Visit (default)"
      }
    }
   ,{
      "id":"54617886730996150"
     ,"Identification":{
        "Name":"Update"
       ,"Type":"Execute Code"
      }
     ,"Source":{
        "Location":"Local Database"
       ,"Language":"PL\/SQL"
       ,"PL\/SQL Code":"apex_util.reply_to_feedback (\n    p_feedback_id        =\u003E :P10024_ID,\n    p_status             =\u003E :P10024_FEEDBACK_STATUS,\n    p_public_response    =\u003E :P10024_RESPONSE );"
      }
     ,"Execution Options":{
        "Sequence":10
       ,"Point":"Processing"
       ,"Run Process":"Once Per Page Visit (default)"
      }
     ,"Success Message":{
        "Success Message":"Action Processed."
      }
     ,"Error":{
        "Display Location":"Inline in Notification"
      }
     ,"Server-side Condition":{
        "When Button Pressed":"SAVE (54600408228996129)"
      }
    }
   ,{
      "id":"54618316956996150"
     ,"Identification":{
        "Name":"Delete"
       ,"Type":"Execute Code"
      }
     ,"Source":{
        "Location":"Local Database"
       ,"Language":"PL\/SQL"
       ,"PL\/SQL Code":"apex_util.delete_feedback (\n    p_feedback_id        =\u003E :P10024_ID );"
      }
     ,"Execution Options":{
        "Sequence":20
       ,"Point":"Processing"
       ,"Run Process":"Once Per Page Visit (default)"
      }
     ,"Success Message":{
        "Success Message":"Action Processed."
      }
     ,"Error":{
        "Display Location":"Inline in Notification"
      }
     ,"Server-side Condition":{
        "When Button Pressed":"DELETE (54600636410996129)"
      }
    }
   ,{
      "id":"54618709522996151"
     ,"Identification":{
        "Name":"E.PROPERTY.BUTTON_ACTION.LOV.RESET.D"
       ,"Type":"Clear Session State"
      }
     ,"Settings":{
        "Type":"Clear all Items on the Current Page"
      }
     ,"Execution Options":{
        "Sequence":40
       ,"Point":"Processing"
       ,"Run Process":"Once Per Page Visit (default)"
      }
     ,"Error":{
        "Display Location":"Inline in Notification"
      }
     ,"Server-side Condition":{
        "When Button Pressed":"DELETE (54600636410996129)"
      }
    }
   ,{
      "id":"54619090790996151"
     ,"Identification":{
        "Name":"Close Dialog"
       ,"Type":"Close Dialog"
      }
     ,"Execution Options":{
        "Sequence":50
       ,"Point":"Processing"
       ,"Run Process":"Once Per Page Visit (default)"
      }
     ,"Error":{
        "Display Location":"Inline in Notification"
      }
    }
  ]
}
